gicha/__init__.py
gicha/__main__.py
gicha/core.py
gicha/version.py
gicha/mygit/__init__.py
gicha/myos/__init__.py
gicha/myrich/__init__.py
gicha/sed/__init__.py
gicha-1.2.0.dist-info/LICENSE
gicha-1.2.0.dist-info/METADATA
gicha-1.2.0.dist-info/WHEEL
gicha-1.2.0.dist-info/top_level.txt
gicha-1.2.0.dist-info/RECORD
