Metadata-Version: 2.1
Name: gicha
Version: 1.2.0
Summary: Operating Chalice from Github
Home-page: https://github.com/hei-school/gicha-cli
Author: HEI
Author-email: contact@hei.school
License: MIT
License-File: LICENSE
Requires-Dist: pyyaml
Requires-Dist: fire
Requires-Dist: gitpython
Requires-Dist: rich
